{
  "id": "20260402_142405",
  "label": "stressed",
  "started_at": "2026-04-02T14:24:05",
  "stopped_at": "2026-04-02T14:29:52.387000",
  "readings": [
    {
      "ts": "2026-04-02T14:24:05",
      "bpm": 96.1,
      "temp_c": 26.61,
      "fsr_raw": 449,
      "stress_score": 0.343,
      "rr_intervals": [
        629.6569890622502,
        625.9878925356031,
        634.2595019866783,
        628.2139881034814
      ]
    },
    {
      "ts": "2026-04-02T14:24:08.069000",
      "bpm": 95.0,
      "temp_c": 26.63,
      "fsr_raw": 311,
      "stress_score": 0.666,
      "rr_intervals": [
        624.6273099469432,
        627.2191564798125,
        639.5149682596514,
        637.8406117678674
      ]
    },
    {
      "ts": "2026-04-02T14:24:11.414000",
      "bpm": 97.9,
      "temp_c": 26.7,
      "fsr_raw": 237,
      "stress_score": null,
      "rr_intervals": [
        626.0701179619705,
        612.2584178621851,
        610.7933138768811,
        613.8205822110904
      ]
    },
    {
      "ts": "2026-04-02T14:24:14.654000",
      "bpm": 93.4,
      "temp_c": 26.93,
      "fsr_raw": 320,
      "stress_score": 0.235,
      "rr_intervals": [
        656.0671176738316,
        639.9717566036617,
        647.5280138243955,
        649.3361543146624
      ]
    },
    {
      "ts": "2026-04-02T14:24:17.563000",
      "bpm": 93.8,
      "temp_c": 27.01,
      "fsr_raw": 429,
      "stress_score": 0.666,
      "rr_intervals": [
        648.1429381691751,
        642.481817195023,
        637.8917445383848,
        642.2163483220968
      ]
    },
    {
      "ts": "2026-04-02T14:24:20.726000",
      "bpm": 95.1,
      "temp_c": 26.9,
      "fsr_raw": 140,
      "stress_score": 0.527,
      "rr_intervals": [
        629.4469561094372,
        635.7421985936944,
        626.7148454701257,
        638.9983325768242
      ]
    },
    {
      "ts": "2026-04-02T14:24:23.429000",
      "bpm": 98.2,
      "temp_c": 26.99,
      "fsr_raw": 672,
      "stress_score": 0.313,
      "rr_intervals": [
        604.498709914811,
        619.232919500114,
        609.3799445763044,
        623.6326811187862
      ]
    },
    {
      "ts": "2026-04-02T14:24:26.776000",
      "bpm": 97.2,
      "temp_c": 26.89,
      "fsr_raw": 353,
      "stress_score": 0.254,
      "rr_intervals": [
        623.4501000048512,
        613.5510919732181,
        614.5124300649121,
        612.9402853627223
      ]
    },
    {
      "ts": "2026-04-02T14:24:30.078000",
      "bpm": 100.2,
      "temp_c": 27.19,
      "fsr_raw": 252,
      "stress_score": 0.78,
      "rr_intervals": [
        595.5930771340005,
        602.0908487374849,
        593.7057772319143,
        588.153672553651
      ]
    },
    {
      "ts": "2026-04-02T14:24:32.893000",
      "bpm": 99.8,
      "temp_c": 27.5,
      "fsr_raw": 338,
      "stress_score": 0.798,
      "rr_intervals": [
        605.8261408570197,
        602.7071029203611,
        612.1992402548204,
        605.0074929675797
      ]
    },
    {
      "ts": "2026-04-02T14:24:35.706000",
      "bpm": 96.5,
      "temp_c": 27.74,
      "fsr_raw": 285,
      "stress_score": 0.76,
      "rr_intervals": [
        610.9726017055632,
        618.5208589091549,
        615.9061393592706,
        618.0292781833742
      ]
    },
    {
      "ts": "2026-04-02T14:24:38.917000",
      "bpm": 97.5,
      "temp_c": 27.46,
      "fsr_raw": 339,
      "stress_score": 0.736,
      "rr_intervals": [
        629.2207992516219,
        614.4519047576214,
        612.5254492939125,
        603.4736995841475
      ]
    },
    {
      "ts": "2026-04-02T14:24:42.014000",
      "bpm": 96.9,
      "temp_c": 27.38,
      "fsr_raw": 403,
      "stress_score": 0.648,
      "rr_intervals": [
        617.0923491690796,
        618.6544777384081,
        599.2251704859625,
        625.6139696772852
      ]
    },
    {
      "ts": "2026-04-02T14:24:44.730000",
      "bpm": 101.8,
      "temp_c": 27.48,
      "fsr_raw": 170,
      "stress_score": 0.633,
      "rr_intervals": [
        589.7008625122979,
        564.56809822639,
        590.7571651617656,
        579.2916510580872
      ]
    },
    {
      "ts": "2026-04-02T14:24:47.583000",
      "bpm": 104.5,
      "temp_c": 27.61,
      "fsr_raw": 429,
      "stress_score": 0.605,
      "rr_intervals": [
        574.5956251300447,
        563.2289579697643,
        581.979678256934,
        567.6282445590815
      ]
    },
    {
      "ts": "2026-04-02T14:24:50.495000",
      "bpm": 107.1,
      "temp_c": 27.37,
      "fsr_raw": 15,
      "stress_score": 0.904,
      "rr_intervals": [
        546.8860805422418,
        567.2486803742265,
        572.3107036665641,
        565.8792439233684
      ]
    },
    {
      "ts": "2026-04-02T14:24:53.817000",
      "bpm": 113.5,
      "temp_c": 27.43,
      "fsr_raw": 68,
      "stress_score": 0.936,
      "rr_intervals": [
        525.0133636397936,
        518.5640718186721,
        508.3706594580483,
        516.5291537766433
      ]
    },
    {
      "ts": "2026-04-02T14:24:56.618000",
      "bpm": 117.8,
      "temp_c": 27.61,
      "fsr_raw": 342,
      "stress_score": 0.647,
      "rr_intervals": [
        509.4421961923069,
        503.7899353251455,
        507.7123106898392,
        493.4839924832886
      ]
    },
    {
      "ts": "2026-04-02T14:24:59.553000",
      "bpm": 115.9,
      "temp_c": 27.74,
      "fsr_raw": 210,
      "stress_score": 0.937,
      "rr_intervals": [
        518.4443826751112,
        517.9694546464721,
        512.7863021932367,
        506.7285376488479
      ]
    },
    {
      "ts": "2026-04-02T14:25:02.830000",
      "bpm": 118.3,
      "temp_c": 27.51,
      "fsr_raw": 218,
      "stress_score": 0.726,
      "rr_intervals": [
        491.3676708932176,
        512.8009952411392,
        504.2466410388534,
        511.01896725668814
      ]
    },
    {
      "ts": "2026-04-02T14:25:05.569000",
      "bpm": 114.5,
      "temp_c": 27.34,
      "fsr_raw": 289,
      "stress_score": 0.626,
      "rr_intervals": [
        527.8196841380521,
        509.090759209197,
        531.6301356325162,
        512.6241275243241
      ]
    },
    {
      "ts": "2026-04-02T14:25:08.673000",
      "bpm": 119.1,
      "temp_c": 27.34,
      "fsr_raw": 436,
      "stress_score": 0.863,
      "rr_intervals": [
        503.65761575824934,
        512.4644488450892,
        516.9615680520176,
        511.89215171033607
      ]
    },
    {
      "ts": "2026-04-02T14:25:11.578000",
      "bpm": 116.3,
      "temp_c": 27.67,
      "fsr_raw": 629,
      "stress_score": 0.678,
      "rr_intervals": [
        511.7262095835415,
        510.9463821146882,
        532.2922854897826,
        509.92333018442605
      ]
    },
    {
      "ts": "2026-04-02T14:25:14.362000",
      "bpm": 108.8,
      "temp_c": 27.55,
      "fsr_raw": 219,
      "stress_score": 0.609,
      "rr_intervals": [
        554.2884583632086,
        554.4030936961243,
        553.625667064143,
        547.5726341033688
      ]
    },
    {
      "ts": "2026-04-02T14:25:17.686000",
      "bpm": 110.3,
      "temp_c": 27.54,
      "fsr_raw": 302,
      "stress_score": 0.779,
      "rr_intervals": [
        554.0694858872537,
        541.9439373473251,
        556.1205517311381,
        544.3555408097109
      ]
    },
    {
      "ts": "2026-04-02T14:25:21",
      "bpm": 109.3,
      "temp_c": 27.53,
      "fsr_raw": 284,
      "stress_score": 0.802,
      "rr_intervals": [
        546.6359542134456,
        552.4075664568569,
        563.4665393554207,
        558.0765392539312
      ]
    },
    {
      "ts": "2026-04-02T14:25:24.053000",
      "bpm": 112.3,
      "temp_c": 27.45,
      "fsr_raw": 270,
      "stress_score": 0.719,
      "rr_intervals": [
        540.268584633784,
        533.0339222285372,
        537.1812202230558,
        522.3821332551154
      ]
    },
    {
      "ts": "2026-04-02T14:25:27.068000",
      "bpm": 110.9,
      "temp_c": 27.49,
      "fsr_raw": 374,
      "stress_score": 0.804,
      "rr_intervals": [
        545.6655783486747,
        532.3840807907774,
        546.5620185054333,
        538.4371392230499
      ]
    },
    {
      "ts": "2026-04-02T14:25:30.310000",
      "bpm": 106.1,
      "temp_c": 27.46,
      "fsr_raw": 287,
      "stress_score": 0.829,
      "rr_intervals": [
        565.2739723197406,
        568.4061054190809,
        569.3924814501842,
        570.3613900531801
      ]
    },
    {
      "ts": "2026-04-02T14:25:33.038000",
      "bpm": 106.5,
      "temp_c": 27.69,
      "fsr_raw": 70,
      "stress_score": 0.898,
      "rr_intervals": [
        543.7940794271495,
        569.2509430296925,
        563.659149339039,
        574.5776165848125
      ]
    },
    {
      "ts": "2026-04-02T14:25:35.939000",
      "bpm": 101.6,
      "temp_c": 27.66,
      "fsr_raw": 197,
      "stress_score": 0.843,
      "rr_intervals": [
        599.5371430661692,
        581.4910196943076,
        584.262221583957,
        600.7648565859756
      ]
    },
    {
      "ts": "2026-04-02T14:25:38.966000",
      "bpm": 102.4,
      "temp_c": 27.47,
      "fsr_raw": 234,
      "stress_score": 0.743,
      "rr_intervals": [
        571.6505325140892,
        583.634147593999,
        608.835885140268,
        582.1922453071458
      ]
    },
    {
      "ts": "2026-04-02T14:25:41.788000",
      "bpm": 103.2,
      "temp_c": 27.57,
      "fsr_raw": 356,
      "stress_score": 0.588,
      "rr_intervals": [
        582.3753950662469,
        590.1350040651017,
        573.1005715807356,
        585.0364972238297
      ]
    },
    {
      "ts": "2026-04-02T14:25:44.925000",
      "bpm": 103.5,
      "temp_c": 27.64,
      "fsr_raw": 530,
      "stress_score": 0.59,
      "rr_intervals": [
        576.1067029751749,
        564.3583755514333,
        571.8266816100747,
        586.4871771668735
      ]
    },
    {
      "ts": "2026-04-02T14:25:48.307000",
      "bpm": 101.3,
      "temp_c": 27.61,
      "fsr_raw": 200,
      "stress_score": 0.661,
      "rr_intervals": [
        580.2481691480508,
        592.0662134222782,
        594.0371671925222,
        571.4829401989026
      ]
    },
    {
      "ts": "2026-04-02T14:25:51.562000",
      "bpm": 102.8,
      "temp_c": 27.65,
      "fsr_raw": 244,
      "stress_score": 0.743,
      "rr_intervals": [
        590.9187715344561,
        577.4042430488813,
        580.8936899587229,
        586.8080684319013
      ]
    },
    {
      "ts": "2026-04-02T14:25:54.839000",
      "bpm": 100.7,
      "temp_c": 27.81,
      "fsr_raw": 460,
      "stress_score": 0.581,
      "rr_intervals": [
        602.8399268394595,
        599.7913340103725,
        605.4278008675018,
        596.1388909757619
      ]
    },
    {
      "ts": "2026-04-02T14:25:58.164000",
      "bpm": 100.0,
      "temp_c": 27.71,
      "fsr_raw": 377,
      "stress_score": 0.774,
      "rr_intervals": [
        602.8499903195384,
        608.4435800603595,
        596.7225769207081,
        603.9537429079958
      ]
    },
    {
      "ts": "2026-04-02T14:26:01.416000",
      "bpm": 101.2,
      "temp_c": 27.75,
      "fsr_raw": 421,
      "stress_score": 0.606,
      "rr_intervals": [
        594.4561175053084,
        592.1805860892782,
        602.1845951571798,
        590.2296111876215
      ]
    },
    {
      "ts": "2026-04-02T14:26:04.213000",
      "bpm": 100.5,
      "temp_c": 27.74,
      "fsr_raw": 528,
      "stress_score": 0.817,
      "rr_intervals": [
        608.0561971604135,
        603.1766425832012,
        601.2564928010237,
        603.4854067763316
      ]
    },
    {
      "ts": "2026-04-02T14:26:07.076000",
      "bpm": 100.0,
      "temp_c": 27.6,
      "fsr_raw": 553,
      "stress_score": 0.696,
      "rr_intervals": [
        598.7465823327407,
        593.5292489516901,
        604.9970105703345,
        605.8258092041585
      ]
    },
    {
      "ts": "2026-04-02T14:26:10.426000",
      "bpm": 99.6,
      "temp_c": 27.8,
      "fsr_raw": 349,
      "stress_score": 0.932,
      "rr_intervals": [
        599.4713426935895,
        603.3303284564801,
        605.5495134528443,
        606.6054196484523
      ]
    },
    {
      "ts": "2026-04-02T14:26:13.681000",
      "bpm": 24.4,
      "temp_c": 27.74,
      "fsr_raw": 135,
      "stress_score": 0.809,
      "rr_intervals": [
        1500.0,
        1500.0,
        1496.8325670904376,
        1500.0
      ]
    },
    {
      "ts": "2026-04-02T14:26:16.955000",
      "bpm": 105.9,
      "temp_c": 27.88,
      "fsr_raw": 453,
      "stress_score": 0.845,
      "rr_intervals": [
        572.3903996774841,
        566.9099417507385,
        565.5075398072421,
        571.7603468705566
      ]
    },
    {
      "ts": "2026-04-02T14:26:19.867000",
      "bpm": 100.5,
      "temp_c": 27.71,
      "fsr_raw": 54,
      "stress_score": 0.899,
      "rr_intervals": [
        602.2545199660489,
        587.6870498363081,
        595.8258284460509,
        592.4240937958506
      ]
    },
    {
      "ts": "2026-04-02T14:26:23.093000",
      "bpm": 102.6,
      "temp_c": 27.94,
      "fsr_raw": 220,
      "stress_score": 0.561,
      "rr_intervals": [
        579.9581720697485,
        592.6511155660532,
        574.7257140738192,
        594.8259542909974
      ]
    },
    {
      "ts": "2026-04-02T14:26:25.988000",
      "bpm": 98.8,
      "temp_c": 27.77,
      "fsr_raw": 405,
      "stress_score": 0.661,
      "rr_intervals": [
        606.0433689732488,
        605.5017226653204,
        606.90625953588,
        608.4790352624448
      ]
    },
    {
      "ts": "2026-04-02T14:26:28.839000",
      "bpm": 99.5,
      "temp_c": 27.86,
      "fsr_raw": 205,
      "stress_score": 0.797,
      "rr_intervals": [
        597.6822021373015,
        606.8676262179229,
        598.2121677181732,
        600.1816534686177
      ]
    },
    {
      "ts": "2026-04-02T14:26:32.111000",
      "bpm": 99.7,
      "temp_c": 27.87,
      "fsr_raw": 630,
      "stress_score": 0.891,
      "rr_intervals": [
        611.9882357573096,
        590.9418758207775,
        589.5591130668018,
        597.1108339274449
      ]
    },
    {
      "ts": "2026-04-02T14:26:35.439000",
      "bpm": 99.1,
      "temp_c": 27.85,
      "fsr_raw": 445,
      "stress_score": 0.714,
      "rr_intervals": [
        606.7177985993394,
        599.3693652770551,
        604.5397425576202,
        597.5671581521617
      ]
    },
    {
      "ts": "2026-04-02T14:26:38.573000",
      "bpm": 101.6,
      "temp_c": 27.55,
      "fsr_raw": 345,
      "stress_score": 0.645,
      "rr_intervals": [
        587.9905010045304,
        585.6410080850627,
        595.4189860847507,
        597.1377924643299
      ]
    },
    {
      "ts": "2026-04-02T14:26:41.941000",
      "bpm": 105.8,
      "temp_c": 27.43,
      "fsr_raw": 116,
      "stress_score": 0.766,
      "rr_intervals": [
        555.8313735816579,
        575.2005117428798,
        577.4582618323276,
        584.3726904014178
      ]
    },
    {
      "ts": "2026-04-02T14:26:44.957000",
      "bpm": 106.3,
      "temp_c": 27.36,
      "fsr_raw": 299,
      "stress_score": 0.679,
      "rr_intervals": [
        569.7254085357181,
        560.0980569886667,
        569.582448769437,
        576.6213797076912
      ]
    },
    {
      "ts": "2026-04-02T14:26:47.879000",
      "bpm": 107.6,
      "temp_c": 27.42,
      "fsr_raw": 600,
      "stress_score": 0.886,
      "rr_intervals": [
        556.9620686130756,
        558.2743939619263,
        562.8039057625911,
        571.9645801185541
      ]
    },
    {
      "ts": "2026-04-02T14:26:50.943000",
      "bpm": 108.1,
      "temp_c": 27.26,
      "fsr_raw": 504,
      "stress_score": 0.637,
      "rr_intervals": [
        549.3337461483859,
        550.6586230453843,
        559.6450706366903,
        564.9531849929607
      ]
    },
    {
      "ts": "2026-04-02T14:26:54.082000",
      "bpm": 105.0,
      "temp_c": 27.23,
      "fsr_raw": 432,
      "stress_score": 0.64,
      "rr_intervals": [
        584.7790149521456,
        563.7679839318113,
        568.3060203909487,
        573.3329725295031
      ]
    },
    {
      "ts": "2026-04-02T14:26:56.968000",
      "bpm": 102.3,
      "temp_c": 26.95,
      "fsr_raw": 482,
      "stress_score": 0.884,
      "rr_intervals": [
        591.1825761022826,
        589.2492164840164,
        585.3034729007933,
        587.4910388656585
      ]
    },
    {
      "ts": "2026-04-02T14:27:00.057000",
      "bpm": 101.4,
      "temp_c": 27.12,
      "fsr_raw": 213,
      "stress_score": 0.779,
      "rr_intervals": [
        593.8761083653338,
        596.930053545379,
        592.0224852295092,
        583.0655873631245
      ]
    },
    {
      "ts": "2026-04-02T14:27:03.282000",
      "bpm": 102.8,
      "temp_c": 27.03,
      "fsr_raw": 231,
      "stress_score": 0.736,
      "rr_intervals": [
        594.1107757113055,
        580.7065776433168,
        576.6041023886994,
        588.0550926608053
      ]
    },
    {
      "ts": "2026-04-02T14:27:06.560000",
      "bpm": 106.2,
      "temp_c": 27.08,
      "fsr_raw": 205,
      "stress_score": 0.762,
      "rr_intervals": [
        561.4617572045072,
        561.9660782994179,
        566.7888674318563,
        542.2981144112767
      ]
    },
    {
      "ts": "2026-04-02T14:27:09.952000",
      "bpm": 103.3,
      "temp_c": 27.11,
      "fsr_raw": 592,
      "stress_score": 0.804,
      "rr_intervals": [
        581.0281067291095,
        582.4866740290776,
        580.5617233356392,
        586.4860851426969
      ]
    },
    {
      "ts": "2026-04-02T14:27:12.999000",
      "bpm": 107.3,
      "temp_c": 27.09,
      "fsr_raw": 129,
      "stress_score": 0.576,
      "rr_intervals": [
        544.4623564026789,
        560.1890852477328,
        561.4686333924121,
        553.4068332106792
      ]
    },
    {
      "ts": "2026-04-02T14:27:15.900000",
      "bpm": 105.0,
      "temp_c": 27.08,
      "fsr_raw": 318,
      "stress_score": 0.786,
      "rr_intervals": [
        572.0207397143241,
        585.9082344058249,
        579.3414500040984,
        550.8511990784922
      ]
    },
    {
      "ts": "2026-04-02T14:27:18.966000",
      "bpm": 103.1,
      "temp_c": 26.85,
      "fsr_raw": 366,
      "stress_score": 0.616,
      "rr_intervals": [
        584.0784131618072,
        587.3314912498664,
        572.978781095705,
        575.0723119585999
      ]
    },
    {
      "ts": "2026-04-02T14:27:21.702000",
      "bpm": 105.6,
      "temp_c": 26.96,
      "fsr_raw": 511,
      "stress_score": 0.619,
      "rr_intervals": [
        555.0194989856383,
        553.2003699760145,
        571.9869196350533,
        572.7930942048895
      ]
    },
    {
      "ts": "2026-04-02T14:27:24.788000",
      "bpm": 106.4,
      "temp_c": 27.06,
      "fsr_raw": 208,
      "stress_score": 0.63,
      "rr_intervals": [
        582.5754909486961,
        547.0319391750456,
        563.188943504316,
        553.9445240438929
      ]
    },
    {
      "ts": "2026-04-02T14:27:27.559000",
      "bpm": 0.2,
      "temp_c": 27.24,
      "fsr_raw": 273,
      "stress_score": 0.689,
      "rr_intervals": [
        1500.0,
        1496.6975830320437,
        1500.0,
        1500.0
      ]
    },
    {
      "ts": "2026-04-02T14:27:30.653000",
      "bpm": 100.7,
      "temp_c": 27.46,
      "fsr_raw": 443,
      "stress_score": 0.652,
      "rr_intervals": [
        588.0233134276449,
        582.8486876539481,
        598.1341947216812,
        591.2814206101468
      ]
    },
    {
      "ts": "2026-04-02T14:27:33.409000",
      "bpm": 93.8,
      "temp_c": 27.34,
      "fsr_raw": 231,
      "stress_score": 0.649,
      "rr_intervals": [
        634.9700997568646,
        632.3360046282429,
        638.3912071083935,
        633.3743096120827
      ]
    },
    {
      "ts": "2026-04-02T14:27:36.486000",
      "bpm": 94.9,
      "temp_c": 27.14,
      "fsr_raw": 317,
      "stress_score": 0.679,
      "rr_intervals": [
        632.7795407482298,
        631.0482843119277,
        638.3415103403124,
        625.1826498113328
      ]
    },
    {
      "ts": "2026-04-02T14:27:39.611000",
      "bpm": 97.3,
      "temp_c": 27.33,
      "fsr_raw": 271,
      "stress_score": 0.582,
      "rr_intervals": [
        620.0131098141462,
        615.1623718634524,
        620.4785605538713,
        616.6197547677353
      ]
    },
    {
      "ts": "2026-04-02T14:27:42.943000",
      "bpm": 99.4,
      "temp_c": 27.09,
      "fsr_raw": 512,
      "stress_score": 0.777,
      "rr_intervals": [
        601.5452927680878,
        600.7180964566127,
        602.2966821453434,
        612.3482462930828
      ]
    },
    {
      "ts": "2026-04-02T14:27:46.101000",
      "bpm": 102.6,
      "temp_c": 26.83,
      "fsr_raw": 524,
      "stress_score": 0.816,
      "rr_intervals": [
        589.8159130099103,
        575.5367027681191,
        587.286421521108,
        579.4600359167865
      ]
    },
    {
      "ts": "2026-04-02T14:27:49.247000",
      "bpm": 100.9,
      "temp_c": 26.85,
      "fsr_raw": 453,
      "stress_score": 0.906,
      "rr_intervals": [
        595.833172969219,
        586.6845937786886,
        580.1993940293848,
        603.1124442338573
      ]
    },
    {
      "ts": "2026-04-02T14:27:52.055000",
      "bpm": 96.4,
      "temp_c": 26.95,
      "fsr_raw": 265,
      "stress_score": 0.742,
      "rr_intervals": [
        613.1109086555796,
        618.6550554756003,
        617.097381506291,
        628.2083646404965
      ]
    },
    {
      "ts": "2026-04-02T14:27:54.797000",
      "bpm": 98.8,
      "temp_c": 26.96,
      "fsr_raw": 353,
      "stress_score": 0.63,
      "rr_intervals": [
        595.6487871732566,
        586.8773644646285,
        613.2788536579766,
        595.4471727973278
      ]
    },
    {
      "ts": "2026-04-02T14:27:57.694000",
      "bpm": 93.9,
      "temp_c": 27.1,
      "fsr_raw": 369,
      "stress_score": 0.758,
      "rr_intervals": [
        642.9289161257984,
        648.6379775138934,
        633.7276367489159,
        635.5251913550237
      ]
    },
    {
      "ts": "2026-04-02T14:28:00.628000",
      "bpm": 92.3,
      "temp_c": 27.29,
      "fsr_raw": 205,
      "stress_score": 0.872,
      "rr_intervals": [
        643.3786457898752,
        652.7939852246571,
        644.9108220892984,
        638.648537934563
      ]
    },
    {
      "ts": "2026-04-02T14:28:03.584000",
      "bpm": 93.8,
      "temp_c": 27.3,
      "fsr_raw": 313,
      "stress_score": 0.811,
      "rr_intervals": [
        643.4444331359006,
        629.5189452659583,
        628.0099045955857,
        641.9046156215945
      ]
    },
    {
      "ts": "2026-04-02T14:28:06.569000",
      "bpm": 90.8,
      "temp_c": 27.37,
      "fsr_raw": 259,
      "stress_score": 0.8,
      "rr_intervals": [
        657.4527742475301,
        659.3153770815863,
        658.4462417504717,
        663.8344677989036
      ]
    },
    {
      "ts": "2026-04-02T14:28:09.931000",
      "bpm": 95.8,
      "temp_c": 27.3,
      "fsr_raw": 225,
      "stress_score": 0.739,
      "rr_intervals": [
        645.365437906353,
        629.9395923083733,
        629.8318780860551,
        629.9871564710409
      ]
    },
    {
      "ts": "2026-04-02T14:28:13.265000",
      "bpm": 94.4,
      "temp_c": 27.21,
      "fsr_raw": 219,
      "stress_score": 0.865,
      "rr_intervals": [
        640.768421981498,
        623.1770266094558,
        635.6447063696945,
        656.7162731541792
      ]
    },
    {
      "ts": "2026-04-02T14:28:16.243000",
      "bpm": 97.2,
      "temp_c": 27.33,
      "fsr_raw": 478,
      "stress_score": 0.81,
      "rr_intervals": [
        614.7723936476575,
        610.9115726184516,
        624.9716994351451,
        605.901603203929
      ]
    },
    {
      "ts": "2026-04-02T14:28:19.276000",
      "bpm": 98.3,
      "temp_c": 27.34,
      "fsr_raw": 484,
      "stress_score": 0.859,
      "rr_intervals": [
        618.5433094764542,
        612.053502321715,
        615.9639027340831,
        606.6782315287426
      ]
    },
    {
      "ts": "2026-04-02T14:28:22.093000",
      "bpm": 95.9,
      "temp_c": 27.49,
      "fsr_raw": 323,
      "stress_score": 0.793,
      "rr_intervals": [
        607.4689237156191,
        634.0802199762269,
        626.5563632310124,
        624.3098641098088
      ]
    },
    {
      "ts": "2026-04-02T14:28:25.106000",
      "bpm": 96.6,
      "temp_c": 27.32,
      "fsr_raw": 219,
      "stress_score": 0.811,
      "rr_intervals": [
        621.5025772613976,
        619.5160427065833,
        618.3670110836516,
        632.4063429604564
      ]
    },
    {
      "ts": "2026-04-02T14:28:28.443000",
      "bpm": 91.7,
      "temp_c": 27.5,
      "fsr_raw": 350,
      "stress_score": 0.595,
      "rr_intervals": [
        653.0463810962901,
        642.4630790493138,
        663.9917120682253,
        650.2107863311688
      ]
    },
    {
      "ts": "2026-04-02T14:28:31.561000",
      "bpm": 95.9,
      "temp_c": 27.49,
      "fsr_raw": 244,
      "stress_score": 0.873,
      "rr_intervals": [
        626.4232256226503,
        623.6840803983241,
        622.337485606611,
        627.6174744454797
      ]
    },
    {
      "ts": "2026-04-02T14:28:34.356000",
      "bpm": 100.8,
      "temp_c": 27.42,
      "fsr_raw": 386,
      "stress_score": 0.907,
      "rr_intervals": [
        598.2323605146346,
        586.1674947166689,
        605.0109848553665,
        591.8535681384142
      ]
    },
    {
      "ts": "2026-04-02T14:28:37.076000",
      "bpm": 95.8,
      "temp_c": 27.14,
      "fsr_raw": 562,
      "stress_score": 0.855,
      "rr_intervals": [
        641.5266083277343,
        626.716620997998,
        617.7043085009861,
        629.155399297098
      ]
    },
    {
      "ts": "2026-04-02T14:28:40.249000",
      "bpm": 98.8,
      "temp_c": 27.16,
      "fsr_raw": 87,
      "stress_score": 0.967,
      "rr_intervals": [
        607.5890231470468,
        605.7814343251895,
        605.3489699178654,
        597.5480213253906
      ]
    },
    {
      "ts": "2026-04-02T14:28:43.309000",
      "bpm": 97.1,
      "temp_c": 26.95,
      "fsr_raw": 118,
      "stress_score": 0.583,
      "rr_intervals": [
        611.3440719394367,
        619.0177055853987,
        611.3625051017516,
        616.99099713768
      ]
    },
    {
      "ts": "2026-04-02T14:28:46.069000",
      "bpm": 100.9,
      "temp_c": 26.92,
      "fsr_raw": 545,
      "stress_score": 0.942,
      "rr_intervals": [
        593.6293045974143,
        590.7990000176252,
        590.4915658198928,
        596.8791972095805
      ]
    },
    {
      "ts": "2026-04-02T14:28:49.445000",
      "bpm": 99.5,
      "temp_c": 27.11,
      "fsr_raw": 290,
      "stress_score": 0.769,
      "rr_intervals": [
        599.2346697994377,
        599.6683421887377,
        606.7890106167098,
        593.7443582489559
      ]
    },
    {
      "ts": "2026-04-02T14:28:52.222000",
      "bpm": 100.9,
      "temp_c": 27.19,
      "fsr_raw": 272,
      "stress_score": 0.92,
      "rr_intervals": [
        605.9901278249503,
        580.1421373771603,
        584.4137898222587,
        601.1597568288264
      ]
    },
    {
      "ts": "2026-04-02T14:28:55.587000",
      "bpm": 102.5,
      "temp_c": 27.26,
      "fsr_raw": 303,
      "stress_score": 0.872,
      "rr_intervals": [
        596.807964204212,
        582.7277598928674,
        593.5148242827169,
        579.9210588207488
      ]
    },
    {
      "ts": "2026-04-02T14:28:58.616000",
      "bpm": 97.3,
      "temp_c": 27.11,
      "fsr_raw": 25,
      "stress_score": 0.83,
      "rr_intervals": [
        621.002283064307,
        630.3384442313362,
        612.1773700102323,
        603.1352183968279
      ]
    },
    {
      "ts": "2026-04-02T14:29:01.539000",
      "bpm": 98.3,
      "temp_c": 26.95,
      "fsr_raw": 246,
      "stress_score": 0.714,
      "rr_intervals": [
        614.2293220349269,
        613.3568135814302,
        605.982840484159,
        612.8679345862992
      ]
    },
    {
      "ts": "2026-04-02T14:29:04.662000",
      "bpm": 94.3,
      "temp_c": 26.93,
      "fsr_raw": 533,
      "stress_score": 0.577,
      "rr_intervals": [
        638.7985286716613,
        636.0882072551354,
        630.4262242671838,
        627.9004997150195
      ]
    },
    {
      "ts": "2026-04-02T14:29:07.771000",
      "bpm": 89.8,
      "temp_c": 26.91,
      "fsr_raw": 378,
      "stress_score": 0.658,
      "rr_intervals": [
        668.0840150403396,
        658.5127717316245,
        658.6908732760191,
        665.8153496080422
      ]
    },
    {
      "ts": "2026-04-02T14:29:10.789000",
      "bpm": 90.2,
      "temp_c": 26.78,
      "fsr_raw": 114,
      "stress_score": 0.606,
      "rr_intervals": [
        673.636174393772,
        667.6508646844206,
        661.7845987020224,
        679.7023552831193
      ]
    },
    {
      "ts": "2026-04-02T14:29:13.775000",
      "bpm": 89.8,
      "temp_c": 27.02,
      "fsr_raw": 404,
      "stress_score": 0.83,
      "rr_intervals": [
        666.0180028547691,
        665.5254652386438,
        668.8419067221478,
        669.0904989535168
      ]
    },
    {
      "ts": "2026-04-02T14:29:16.500000",
      "bpm": 91.5,
      "temp_c": 27.13,
      "fsr_raw": 487,
      "stress_score": 0.656,
      "rr_intervals": [
        654.8260215501635,
        647.823083359774,
        660.8606702436797,
        650.8209216423146
      ]
    },
    {
      "ts": "2026-04-02T14:29:19.438000",
      "bpm": 89.5,
      "temp_c": 27.11,
      "fsr_raw": 317,
      "stress_score": 0.849,
      "rr_intervals": [
        681.0084168422698,
        690.5419498782751,
        670.6901170254249,
        680.6105454545873
      ]
    },
    {
      "ts": "2026-04-02T14:29:22.445000",
      "bpm": 92.8,
      "temp_c": 27.06,
      "fsr_raw": 133,
      "stress_score": 0.878,
      "rr_intervals": [
        655.5536038731946,
        646.6764719200677,
        652.4446197296236,
        669.2563312016456
      ]
    },
    {
      "ts": "2026-04-02T14:29:25.182000",
      "bpm": 97.5,
      "temp_c": 27.15,
      "fsr_raw": 309,
      "stress_score": 0.563,
      "rr_intervals": [
        618.920919206989,
        603.632200936545,
        617.2718179687234,
        626.3359653680559
      ]
    },
    {
      "ts": "2026-04-02T14:29:28.105000",
      "bpm": 94.5,
      "temp_c": 26.94,
      "fsr_raw": 435,
      "stress_score": 0.944,
      "rr_intervals": [
        638.4782370058209,
        626.035403595314,
        617.8869013251359,
        646.3661504125788
      ]
    },
    {
      "ts": "2026-04-02T14:29:31.316000",
      "bpm": 91.5,
      "temp_c": 26.9,
      "fsr_raw": 303,
      "stress_score": 0.888,
      "rr_intervals": [
        671.6203057545611,
        649.9512427629554,
        654.0334565495633,
        653.2621882661572
      ]
    },
    {
      "ts": "2026-04-02T14:29:34.484000",
      "bpm": 93.7,
      "temp_c": 27.28,
      "fsr_raw": 472,
      "stress_score": 0.765,
      "rr_intervals": [
        641.8787489053036,
        633.0846905964688,
        640.1016653248457,
        625.2206183374677
      ]
    },
    {
      "ts": "2026-04-02T14:29:37.232000",
      "bpm": 94.0,
      "temp_c": 27.43,
      "fsr_raw": 300,
      "stress_score": 0.965,
      "rr_intervals": [
        640.4529654670821,
        653.8231768376525,
        635.3398859675458,
        633.5141648145743
      ]
    },
    {
      "ts": "2026-04-02T14:29:40.264000",
      "bpm": 97.9,
      "temp_c": 27.51,
      "fsr_raw": 403,
      "stress_score": 0.967,
      "rr_intervals": [
        612.5739926642542,
        611.0361269641838,
        617.5643155670684,
        602.071534520324
      ]
    },
    {
      "ts": "2026-04-02T14:29:43.474000",
      "bpm": 94.6,
      "temp_c": 27.61,
      "fsr_raw": 262,
      "stress_score": 0.74,
      "rr_intervals": [
        630.2088510557585,
        632.043388672047,
        634.8497979586019,
        640.144892817953
      ]
    },
    {
      "ts": "2026-04-02T14:29:46.353000",
      "bpm": 96.5,
      "temp_c": 27.61,
      "fsr_raw": 469,
      "stress_score": 0.851,
      "rr_intervals": [
        623.3704022671213,
        629.945244060716,
        623.027317192329,
        627.4721190750267
      ]
    },
    {
      "ts": "2026-04-02T14:29:49.328000",
      "bpm": 97.7,
      "temp_c": 27.31,
      "fsr_raw": 332,
      "stress_score": 0.628,
      "rr_intervals": [
        614.4365110466742,
        606.1182122331304,
        620.3452191795591,
        609.8289033806528
      ]
    }
  ]
}