{
  "id": "20260407_195405",
  "label": "cognitive_load",
  "started_at": "2026-04-07T19:54:05",
  "stopped_at": "2026-04-07T19:59:18.432000",
  "readings": [
    {
      "ts": "2026-04-07T19:54:05",
      "bpm": 86.5,
      "temp_c": 28.98,
      "fsr_raw": 16,
      "stress_score": null,
      "rr_intervals": [
        714.1199454070752,
        687.9198153795061,
        669.5901374217327,
        714.635765154633
      ]
    },
    {
      "ts": "2026-04-07T19:54:08.391000",
      "bpm": 83.1,
      "temp_c": 29.05,
      "fsr_raw": 11,
      "stress_score": 0.324,
      "rr_intervals": [
        727.9100583995032,
        750.9318709206943,
        713.2038928171568,
        752.1621908200742
      ]
    },
    {
      "ts": "2026-04-07T19:54:11.207000",
      "bpm": 84.6,
      "temp_c": 29.03,
      "fsr_raw": 14,
      "stress_score": 0.208,
      "rr_intervals": [
        711.6473447334622,
        767.4968353216033,
        688.6364796044329,
        691.8037903363639
      ]
    },
    {
      "ts": "2026-04-07T19:54:13.965000",
      "bpm": 85.1,
      "temp_c": 29.1,
      "fsr_raw": 35,
      "stress_score": 0.382,
      "rr_intervals": [
        713.1732823347687,
        721.9631305355932,
        740.5328530974031,
        700.6888548220747
      ]
    },
    {
      "ts": "2026-04-07T19:54:17.318000",
      "bpm": 84.6,
      "temp_c": 29.08,
      "fsr_raw": 29,
      "stress_score": 0.204,
      "rr_intervals": [
        711.4250596465679,
        703.1474102174285,
        719.9350310760653,
        692.4124757094571
      ]
    },
    {
      "ts": "2026-04-07T19:54:20.678000",
      "bpm": 83.9,
      "temp_c": 28.86,
      "fsr_raw": 21,
      "stress_score": 0.269,
      "rr_intervals": [
        726.385064642421,
        711.1001865437463,
        682.3182669533255,
        708.0241731583343
      ]
    },
    {
      "ts": "2026-04-07T19:54:23.580000",
      "bpm": 84.5,
      "temp_c": 28.64,
      "fsr_raw": 19,
      "stress_score": 0.458,
      "rr_intervals": [
        713.4920388864942,
        757.0323815616567,
        722.6277893341439,
        692.6719905134836
      ]
    },
    {
      "ts": "2026-04-07T19:54:26.838000",
      "bpm": 87.6,
      "temp_c": 28.7,
      "fsr_raw": 6,
      "stress_score": 0.385,
      "rr_intervals": [
        707.0697321104998,
        686.6694253046979,
        683.2092992197049,
        657.2856770633781
      ]
    },
    {
      "ts": "2026-04-07T19:54:29.912000",
      "bpm": 89.9,
      "temp_c": 28.71,
      "fsr_raw": 23,
      "stress_score": 0.503,
      "rr_intervals": [
        692.6510973999792,
        655.5921457008537,
        665.9263874043129,
        684.3128775048544
      ]
    },
    {
      "ts": "2026-04-07T19:54:32.762000",
      "bpm": 88.9,
      "temp_c": 28.73,
      "fsr_raw": 16,
      "stress_score": 0.816,
      "rr_intervals": [
        659.7310360137606,
        668.5818243395336,
        722.3692134456263,
        665.1791278579917
      ]
    },
    {
      "ts": "2026-04-07T19:54:35.608000",
      "bpm": 90.9,
      "temp_c": 28.8,
      "fsr_raw": 8,
      "stress_score": 0.809,
      "rr_intervals": [
        677.0222957588381,
        681.7825634360674,
        640.0905472231435,
        676.3060133494948
      ]
    },
    {
      "ts": "2026-04-07T19:54:38.463000",
      "bpm": 91.7,
      "temp_c": 28.69,
      "fsr_raw": 22,
      "stress_score": 0.536,
      "rr_intervals": [
        679.1997867308748,
        704.4157483694497,
        640.2448085895369,
        669.4721806011074
      ]
    },
    {
      "ts": "2026-04-07T19:54:41.291000",
      "bpm": 88.0,
      "temp_c": 28.72,
      "fsr_raw": 21,
      "stress_score": 0.594,
      "rr_intervals": [
        664.582677150822,
        664.5904254198332,
        663.2164056851166,
        662.3596603213866
      ]
    },
    {
      "ts": "2026-04-07T19:54:44.293000",
      "bpm": 88.8,
      "temp_c": 28.66,
      "fsr_raw": 20,
      "stress_score": 0.419,
      "rr_intervals": [
        652.2822242680596,
        664.9531649702884,
        674.6161722928603,
        661.1364275288128
      ]
    },
    {
      "ts": "2026-04-07T19:54:47.534000",
      "bpm": 89.4,
      "temp_c": 28.46,
      "fsr_raw": 25,
      "stress_score": 0.497,
      "rr_intervals": [
        695.9615021507813,
        668.5205772409284,
        669.1381877122587,
        655.3954501492514
      ]
    },
    {
      "ts": "2026-04-07T19:54:50.649000",
      "bpm": 89.2,
      "temp_c": 28.74,
      "fsr_raw": 19,
      "stress_score": 0.666,
      "rr_intervals": [
        673.8638646071892,
        679.6456874016471,
        647.8449581175573,
        656.000291205306
      ]
    },
    {
      "ts": "2026-04-07T19:54:53.552000",
      "bpm": 88.9,
      "temp_c": 28.86,
      "fsr_raw": 17,
      "stress_score": 0.765,
      "rr_intervals": [
        691.879393176918,
        654.4143646518976,
        668.5127325750004,
        676.009332120042
      ]
    },
    {
      "ts": "2026-04-07T19:54:56.280000",
      "bpm": 89.8,
      "temp_c": 28.82,
      "fsr_raw": 30,
      "stress_score": 0.703,
      "rr_intervals": [
        674.4752247681118,
        662.1800972101129,
        674.2107606267119,
        665.9189752072245
      ]
    },
    {
      "ts": "2026-04-07T19:54:59.240000",
      "bpm": 90.4,
      "temp_c": 28.8,
      "fsr_raw": 25,
      "stress_score": 0.584,
      "rr_intervals": [
        673.60682256001,
        657.3024061276103,
        670.6775478448706,
        672.8614095775956
      ]
    },
    {
      "ts": "2026-04-07T19:55:02.634000",
      "bpm": 88.4,
      "temp_c": 28.94,
      "fsr_raw": 12,
      "stress_score": 0.772,
      "rr_intervals": [
        670.8820389165178,
        688.6911580700483,
        695.0391593071466,
        671.3817652430594
      ]
    },
    {
      "ts": "2026-04-07T19:55:05.378000",
      "bpm": 88.2,
      "temp_c": 28.77,
      "fsr_raw": 13,
      "stress_score": 0.588,
      "rr_intervals": [
        727.2129720844267,
        674.611433300416,
        645.2937942316781,
        716.4685323190648
      ]
    },
    {
      "ts": "2026-04-07T19:55:08.642000",
      "bpm": 87.5,
      "temp_c": 28.74,
      "fsr_raw": 25,
      "stress_score": 0.527,
      "rr_intervals": [
        659.054868756255,
        690.9304397108458,
        657.1754680350859,
        653.852096734104
      ]
    },
    {
      "ts": "2026-04-07T19:55:11.648000",
      "bpm": 87.3,
      "temp_c": 28.89,
      "fsr_raw": 15,
      "stress_score": 0.508,
      "rr_intervals": [
        677.5389619218118,
        671.0267098417398,
        696.8475532811277,
        701.2435654008088
      ]
    },
    {
      "ts": "2026-04-07T19:55:14.515000",
      "bpm": 89.5,
      "temp_c": 29.1,
      "fsr_raw": 14,
      "stress_score": 0.474,
      "rr_intervals": [
        636.6684483351399,
        683.4208807934139,
        667.9356035430995,
        672.0326065263139
      ]
    },
    {
      "ts": "2026-04-07T19:55:17.398000",
      "bpm": 90.9,
      "temp_c": 29.09,
      "fsr_raw": 43,
      "stress_score": 0.601,
      "rr_intervals": [
        690.0828798433764,
        665.1310875632093,
        682.8642340458467,
        666.1910583065779
      ]
    },
    {
      "ts": "2026-04-07T19:55:20.564000",
      "bpm": 91.9,
      "temp_c": 29.1,
      "fsr_raw": 17,
      "stress_score": 0.646,
      "rr_intervals": [
        643.1478371711736,
        637.2800406766555,
        680.5656632338006,
        628.2520274728696
      ]
    },
    {
      "ts": "2026-04-07T19:55:23.624000",
      "bpm": 92.9,
      "temp_c": 29.07,
      "fsr_raw": 17,
      "stress_score": 0.4,
      "rr_intervals": [
        669.6691798962319,
        641.3112790305448,
        630.408491045077,
        623.3934212593182
      ]
    },
    {
      "ts": "2026-04-07T19:55:26.613000",
      "bpm": 91.6,
      "temp_c": 29.24,
      "fsr_raw": 18,
      "stress_score": 0.594,
      "rr_intervals": [
        654.3463084343687,
        666.88792949716,
        664.6059885963246,
        627.6115709768912
      ]
    },
    {
      "ts": "2026-04-07T19:55:29.360000",
      "bpm": 93.3,
      "temp_c": 29.29,
      "fsr_raw": 23,
      "stress_score": 0.54,
      "rr_intervals": [
        634.6665792566075,
        660.6834049753234,
        665.3971540193379,
        645.3591136347677
      ]
    },
    {
      "ts": "2026-04-07T19:55:32.239000",
      "bpm": 93.5,
      "temp_c": 29.2,
      "fsr_raw": 24,
      "stress_score": 0.387,
      "rr_intervals": [
        627.956068429029,
        649.4240237616117,
        595.9252424000914,
        639.2671124245088
      ]
    },
    {
      "ts": "2026-04-07T19:55:35.147000",
      "bpm": 90.9,
      "temp_c": 29.02,
      "fsr_raw": 17,
      "stress_score": 0.668,
      "rr_intervals": [
        631.409980300503,
        668.051663673192,
        670.2094821990158,
        647.2811742132718
      ]
    },
    {
      "ts": "2026-04-07T19:55:38.199000",
      "bpm": 12.5,
      "temp_c": 29.04,
      "fsr_raw": 28,
      "stress_score": 0.551,
      "rr_intervals": [
        1500.0,
        1461.7103304937145,
        1500.0,
        1500.0
      ]
    },
    {
      "ts": "2026-04-07T19:55:41.364000",
      "bpm": 94.0,
      "temp_c": 29.07,
      "fsr_raw": 27,
      "stress_score": 0.516,
      "rr_intervals": [
        632.7142566418472,
        598.4770892746367,
        646.6366453483078,
        656.8907387308936
      ]
    },
    {
      "ts": "2026-04-07T19:55:44.731000",
      "bpm": 92.0,
      "temp_c": 29.04,
      "fsr_raw": 25,
      "stress_score": 0.437,
      "rr_intervals": [
        661.8282099554402,
        660.5982471048025,
        648.515271339795,
        613.893742227641
      ]
    },
    {
      "ts": "2026-04-07T19:55:47.673000",
      "bpm": 91.7,
      "temp_c": 29.03,
      "fsr_raw": 15,
      "stress_score": 0.407,
      "rr_intervals": [
        672.4580811278444,
        646.4718295560411,
        660.1215231760777,
        646.7586881374439
      ]
    },
    {
      "ts": "2026-04-07T19:55:50.572000",
      "bpm": 91.4,
      "temp_c": 29.07,
      "fsr_raw": 9,
      "stress_score": 0.533,
      "rr_intervals": [
        670.561969846926,
        663.225912314281,
        665.1036691756302,
        652.0023382799621
      ]
    },
    {
      "ts": "2026-04-07T19:55:53.297000",
      "bpm": 90.1,
      "temp_c": 29.2,
      "fsr_raw": 13,
      "stress_score": 0.401,
      "rr_intervals": [
        645.7479564623453,
        678.6537393425957,
        684.455145388711,
        665.6039628601264
      ]
    },
    {
      "ts": "2026-04-07T19:55:56.636000",
      "bpm": 91.6,
      "temp_c": 29.17,
      "fsr_raw": 13,
      "stress_score": 0.753,
      "rr_intervals": [
        671.5727302508191,
        669.2642479771665,
        674.5420646342371,
        615.547613129834
      ]
    },
    {
      "ts": "2026-04-07T19:55:59.790000",
      "bpm": 13.2,
      "temp_c": 29.26,
      "fsr_raw": 16,
      "stress_score": 0.467,
      "rr_intervals": [
        1500.0,
        1500.0,
        1484.2363221880066,
        1500.0
      ]
    },
    {
      "ts": "2026-04-07T19:56:02.968000",
      "bpm": 88.5,
      "temp_c": 29.25,
      "fsr_raw": 30,
      "stress_score": 0.617,
      "rr_intervals": [
        677.631305629426,
        692.3228973905317,
        671.2085109402666,
        682.1494366614575
      ]
    },
    {
      "ts": "2026-04-07T19:56:06.346000",
      "bpm": 89.1,
      "temp_c": 29.22,
      "fsr_raw": 26,
      "stress_score": 0.761,
      "rr_intervals": [
        688.811064410466,
        668.4230297108337,
        684.5027544560642,
        664.3154567661726
      ]
    },
    {
      "ts": "2026-04-07T19:56:09.291000",
      "bpm": 17.8,
      "temp_c": 29.36,
      "fsr_raw": 28,
      "stress_score": 0.785,
      "rr_intervals": [
        1490.8586158710375,
        1500.0,
        1500.0,
        1487.8566191398077
      ]
    },
    {
      "ts": "2026-04-07T19:56:12.440000",
      "bpm": 84.9,
      "temp_c": 29.24,
      "fsr_raw": 20,
      "stress_score": 0.41,
      "rr_intervals": [
        735.1363218515455,
        708.3449482603833,
        713.6920509274894,
        749.78881011557
      ]
    },
    {
      "ts": "2026-04-07T19:56:15.786000",
      "bpm": 86.5,
      "temp_c": 29.41,
      "fsr_raw": 22,
      "stress_score": 0.397,
      "rr_intervals": [
        695.5589965222201,
        677.8114873909561,
        691.8600119567593,
        688.6531395495952
      ]
    },
    {
      "ts": "2026-04-07T19:56:19.106000",
      "bpm": 87.6,
      "temp_c": 29.43,
      "fsr_raw": 17,
      "stress_score": 0.681,
      "rr_intervals": [
        673.6920038766674,
        693.3890068599899,
        704.9431636876869,
        690.0084549195963
      ]
    },
    {
      "ts": "2026-04-07T19:56:22.302000",
      "bpm": 86.4,
      "temp_c": 29.37,
      "fsr_raw": 20,
      "stress_score": 0.529,
      "rr_intervals": [
        700.8505079589523,
        689.680246541068,
        683.7869969889673,
        682.9685558038921
      ]
    },
    {
      "ts": "2026-04-07T19:56:25.074000",
      "bpm": 85.1,
      "temp_c": 29.39,
      "fsr_raw": 39,
      "stress_score": 0.726,
      "rr_intervals": [
        719.3351874201342,
        684.1934089942371,
        711.1002065331311,
        700.4077496715522
      ]
    },
    {
      "ts": "2026-04-07T19:56:28.280000",
      "bpm": 86.3,
      "temp_c": 29.42,
      "fsr_raw": 35,
      "stress_score": 0.815,
      "rr_intervals": [
        703.3141069835896,
        682.7808901703521,
        691.9744929894276,
        700.4890418838036
      ]
    },
    {
      "ts": "2026-04-07T19:56:31.333000",
      "bpm": 84.3,
      "temp_c": 29.46,
      "fsr_raw": 19,
      "stress_score": 0.793,
      "rr_intervals": [
        752.3790420474613,
        687.9660368490574,
        721.1109339269989,
        684.0602132941121
      ]
    },
    {
      "ts": "2026-04-07T19:56:34.249000",
      "bpm": 85.9,
      "temp_c": 29.59,
      "fsr_raw": 27,
      "stress_score": 0.549,
      "rr_intervals": [
        704.276343620705,
        711.8487903729517,
        711.9355461097746,
        690.9320510370129
      ]
    },
    {
      "ts": "2026-04-07T19:56:36.961000",
      "bpm": 87.4,
      "temp_c": 29.65,
      "fsr_raw": 6,
      "stress_score": 0.7,
      "rr_intervals": [
        694.8061024663588,
        699.801411285551,
        682.3552289576805,
        714.3767687479268
      ]
    },
    {
      "ts": "2026-04-07T19:56:39.995000",
      "bpm": 85.8,
      "temp_c": 29.72,
      "fsr_raw": 22,
      "stress_score": 0.467,
      "rr_intervals": [
        692.7527987170257,
        713.830653726363,
        684.62177928994,
        718.5199784063099
      ]
    },
    {
      "ts": "2026-04-07T19:56:43.128000",
      "bpm": 86.1,
      "temp_c": 29.45,
      "fsr_raw": 14,
      "stress_score": 0.385,
      "rr_intervals": [
        661.7507299379921,
        699.9874451500103,
        668.7762462136816,
        722.6265982684382
      ]
    },
    {
      "ts": "2026-04-07T19:56:45.862000",
      "bpm": 85.9,
      "temp_c": 29.5,
      "fsr_raw": 15,
      "stress_score": 0.535,
      "rr_intervals": [
        684.3494842766509,
        708.1438346904164,
        702.5274080196104,
        702.2494227098322
      ]
    },
    {
      "ts": "2026-04-07T19:56:48.909000",
      "bpm": 88.9,
      "temp_c": 29.51,
      "fsr_raw": 24,
      "stress_score": 0.48,
      "rr_intervals": [
        694.0119968443884,
        698.890951391145,
        666.9389685197123,
        692.5855592594229
      ]
    },
    {
      "ts": "2026-04-07T19:56:52.054000",
      "bpm": 39.6,
      "temp_c": 29.65,
      "fsr_raw": 16,
      "stress_score": 0.634,
      "rr_intervals": [
        1475.3652461184267,
        1484.0112891771184,
        1472.644361964644,
        1461.4640044633954
      ]
    },
    {
      "ts": "2026-04-07T19:56:54.806000",
      "bpm": 87.6,
      "temp_c": 29.57,
      "fsr_raw": 25,
      "stress_score": 0.409,
      "rr_intervals": [
        668.619894570971,
        693.4519493919694,
        701.980307000302,
        673.1022850150613
      ]
    },
    {
      "ts": "2026-04-07T19:56:57.977000",
      "bpm": 88.2,
      "temp_c": 29.61,
      "fsr_raw": 24,
      "stress_score": 0.564,
      "rr_intervals": [
        676.4750650264948,
        686.6495538869573,
        663.1704808925467,
        688.3230713742184
      ]
    },
    {
      "ts": "2026-04-07T19:57:00.995000",
      "bpm": 88.9,
      "temp_c": 29.62,
      "fsr_raw": 29,
      "stress_score": 0.573,
      "rr_intervals": [
        678.393969647192,
        646.4900440652497,
        674.3586930534963,
        682.5816364961146
      ]
    },
    {
      "ts": "2026-04-07T19:57:03.927000",
      "bpm": 88.9,
      "temp_c": 29.45,
      "fsr_raw": 6,
      "stress_score": 0.518,
      "rr_intervals": [
        664.027546768061,
        665.1472868726497,
        659.6254681266762,
        708.2060418941284
      ]
    },
    {
      "ts": "2026-04-07T19:57:06.909000",
      "bpm": 91.7,
      "temp_c": 29.53,
      "fsr_raw": 27,
      "stress_score": 0.709,
      "rr_intervals": [
        694.0866195009837,
        654.2202567133011,
        674.2636875749989,
        672.7200710083649
      ]
    },
    {
      "ts": "2026-04-07T19:57:09.929000",
      "bpm": 93.2,
      "temp_c": 29.64,
      "fsr_raw": 21,
      "stress_score": 0.511,
      "rr_intervals": [
        629.1367806007387,
        618.7577643247946,
        638.2120947020296,
        665.155834062842
      ]
    },
    {
      "ts": "2026-04-07T19:57:12.910000",
      "bpm": 92.5,
      "temp_c": 29.6,
      "fsr_raw": 7,
      "stress_score": 0.562,
      "rr_intervals": [
        658.079258830168,
        627.3019759244532,
        636.3851326196879,
        642.2386854081296
      ]
    },
    {
      "ts": "2026-04-07T19:57:16.221000",
      "bpm": 92.4,
      "temp_c": 29.62,
      "fsr_raw": 27,
      "stress_score": 0.726,
      "rr_intervals": [
        609.2807137914623,
        658.4808700639594,
        652.0955809155918,
        642.8433768846178
      ]
    },
    {
      "ts": "2026-04-07T19:57:18.982000",
      "bpm": 35.2,
      "temp_c": 29.55,
      "fsr_raw": 12,
      "stress_score": 0.614,
      "rr_intervals": [
        1500.0,
        1477.8717748007919,
        1500.0,
        1489.7366245941923
      ]
    },
    {
      "ts": "2026-04-07T19:57:21.980000",
      "bpm": 93.0,
      "temp_c": 29.47,
      "fsr_raw": 20,
      "stress_score": 0.472,
      "rr_intervals": [
        652.6541912928818,
        652.0705264404891,
        646.6936126323355,
        610.0009467980518
      ]
    },
    {
      "ts": "2026-04-07T19:57:25.219000",
      "bpm": 92.2,
      "temp_c": 29.64,
      "fsr_raw": 28,
      "stress_score": 0.434,
      "rr_intervals": [
        653.8596702494553,
        638.6267122828089,
        665.5485847824805,
        626.9915946873213
      ]
    },
    {
      "ts": "2026-04-07T19:57:28.608000",
      "bpm": 88.6,
      "temp_c": 29.65,
      "fsr_raw": 22,
      "stress_score": 0.508,
      "rr_intervals": [
        659.3953141016051,
        663.4367831880766,
        668.3878524867293,
        668.8152194641601
      ]
    },
    {
      "ts": "2026-04-07T19:57:31.511000",
      "bpm": 89.3,
      "temp_c": 29.8,
      "fsr_raw": 21,
      "stress_score": 0.665,
      "rr_intervals": [
        679.362112673525,
        688.598632392863,
        677.0205269462493,
        673.8159413822798
      ]
    },
    {
      "ts": "2026-04-07T19:57:34.690000",
      "bpm": 88.8,
      "temp_c": 29.69,
      "fsr_raw": 27,
      "stress_score": 0.555,
      "rr_intervals": [
        656.8995153659727,
        675.1070024848844,
        683.300017980367,
        686.3344560619929
      ]
    },
    {
      "ts": "2026-04-07T19:57:37.717000",
      "bpm": 86.0,
      "temp_c": 29.74,
      "fsr_raw": 21,
      "stress_score": 0.601,
      "rr_intervals": [
        667.6190713665341,
        674.2001807037374,
        708.461450913206,
        686.5941754559298
      ]
    },
    {
      "ts": "2026-04-07T19:57:40.658000",
      "bpm": 87.0,
      "temp_c": 29.89,
      "fsr_raw": 22,
      "stress_score": 0.44,
      "rr_intervals": [
        666.9083802082035,
        676.3263733311024,
        693.3894958716334,
        693.2211460209134
      ]
    },
    {
      "ts": "2026-04-07T19:57:43.491000",
      "bpm": 85.7,
      "temp_c": 29.79,
      "fsr_raw": 20,
      "stress_score": 0.64,
      "rr_intervals": [
        687.0009928840311,
        699.5905239085956,
        696.1958538133648,
        688.4748376872199
      ]
    },
    {
      "ts": "2026-04-07T19:57:46.579000",
      "bpm": 88.2,
      "temp_c": 29.65,
      "fsr_raw": 18,
      "stress_score": 0.719,
      "rr_intervals": [
        696.8826256511753,
        629.8219178615249,
        669.1619051681643,
        719.6516424667141
      ]
    },
    {
      "ts": "2026-04-07T19:57:49.384000",
      "bpm": 88.3,
      "temp_c": 29.67,
      "fsr_raw": 25,
      "stress_score": 0.745,
      "rr_intervals": [
        688.8075419949914,
        658.1386937173479,
        681.5120273167837,
        679.1086867091763
      ]
    },
    {
      "ts": "2026-04-07T19:57:52.467000",
      "bpm": 88.5,
      "temp_c": 29.6,
      "fsr_raw": 17,
      "stress_score": 0.581,
      "rr_intervals": [
        709.1913677863828,
        691.7568063728999,
        659.7431326755335,
        666.1248691009527
      ]
    },
    {
      "ts": "2026-04-07T19:57:55.730000",
      "bpm": 86.3,
      "temp_c": 29.4,
      "fsr_raw": 23,
      "stress_score": 0.383,
      "rr_intervals": [
        686.9882307206354,
        659.96016928673,
        682.1965855693317,
        715.07896729695
      ]
    },
    {
      "ts": "2026-04-07T19:57:58.866000",
      "bpm": 86.3,
      "temp_c": 29.33,
      "fsr_raw": 29,
      "stress_score": 0.669,
      "rr_intervals": [
        691.4969367477898,
        671.6240955431433,
        705.9783175273641,
        700.4075229224948
      ]
    },
    {
      "ts": "2026-04-07T19:58:02.240000",
      "bpm": 84.8,
      "temp_c": 29.38,
      "fsr_raw": 25,
      "stress_score": 0.384,
      "rr_intervals": [
        701.1137715758249,
        697.8894424662619,
        689.1319009531292,
        714.9417398302797
      ]
    },
    {
      "ts": "2026-04-07T19:58:05.005000",
      "bpm": 86.1,
      "temp_c": 29.3,
      "fsr_raw": 31,
      "stress_score": 0.457,
      "rr_intervals": [
        711.8611541399582,
        688.4205815627819,
        687.5128818454261,
        718.0169160341492
      ]
    },
    {
      "ts": "2026-04-07T19:58:07.799000",
      "bpm": 86.8,
      "temp_c": 29.31,
      "fsr_raw": 21,
      "stress_score": 0.607,
      "rr_intervals": [
        707.7943580956778,
        683.4619341743822,
        688.8958266539183,
        673.8837764869343
      ]
    },
    {
      "ts": "2026-04-07T19:58:10.808000",
      "bpm": 89.0,
      "temp_c": 29.4,
      "fsr_raw": 28,
      "stress_score": 0.386,
      "rr_intervals": [
        705.385939211171,
        673.6472376901822,
        688.6517302874993,
        652.2917388248374
      ]
    },
    {
      "ts": "2026-04-07T19:58:14.177000",
      "bpm": 90.0,
      "temp_c": 29.25,
      "fsr_raw": 25,
      "stress_score": 0.524,
      "rr_intervals": [
        642.3044846124247,
        658.5972542528757,
        681.7631823208754,
        674.8959786084147
      ]
    },
    {
      "ts": "2026-04-07T19:58:17.269000",
      "bpm": 90.6,
      "temp_c": 29.35,
      "fsr_raw": 21,
      "stress_score": 0.552,
      "rr_intervals": [
        671.3081145231491,
        663.1725032733794,
        672.1040048507988,
        667.2585536064656
      ]
    },
    {
      "ts": "2026-04-07T19:58:20.534000",
      "bpm": 88.1,
      "temp_c": 29.06,
      "fsr_raw": 33,
      "stress_score": 0.757,
      "rr_intervals": [
        660.2059769846263,
        655.3177633206309,
        678.058643166004,
        692.1559252659363
      ]
    },
    {
      "ts": "2026-04-07T19:58:23.285000",
      "bpm": 89.2,
      "temp_c": 28.86,
      "fsr_raw": 30,
      "stress_score": 0.753,
      "rr_intervals": [
        658.8019252759651,
        656.6134816363673,
        649.7429450560792,
        694.2378326015812
      ]
    },
    {
      "ts": "2026-04-07T19:58:26.105000",
      "bpm": 87.6,
      "temp_c": 28.76,
      "fsr_raw": 16,
      "stress_score": 0.545,
      "rr_intervals": [
        693.5780078677852,
        708.8200991373076,
        695.6606374863168,
        680.552217837864
      ]
    },
    {
      "ts": "2026-04-07T19:58:28.829000",
      "bpm": 88.4,
      "temp_c": 28.8,
      "fsr_raw": 7,
      "stress_score": 0.604,
      "rr_intervals": [
        717.8422046327562,
        665.5117594604159,
        680.5203802606393,
        694.2000023181454
      ]
    },
    {
      "ts": "2026-04-07T19:58:31.897000",
      "bpm": 91.2,
      "temp_c": 28.7,
      "fsr_raw": 13,
      "stress_score": 0.663,
      "rr_intervals": [
        640.0440380751274,
        649.0934128143006,
        628.0869330153704,
        683.4598496254001
      ]
    },
    {
      "ts": "2026-04-07T19:58:35.196000",
      "bpm": 90.4,
      "temp_c": 28.88,
      "fsr_raw": 20,
      "stress_score": 0.549,
      "rr_intervals": [
        637.4199750587817,
        676.7076569415541,
        644.7241226080083,
        661.707717700165
      ]
    },
    {
      "ts": "2026-04-07T19:58:38.493000",
      "bpm": 91.0,
      "temp_c": 28.79,
      "fsr_raw": 14,
      "stress_score": 0.497,
      "rr_intervals": [
        641.1040016215089,
        680.3614326437705,
        651.0207093609692,
        687.0503139195104
      ]
    },
    {
      "ts": "2026-04-07T19:58:41.531000",
      "bpm": 90.1,
      "temp_c": 28.59,
      "fsr_raw": 6,
      "stress_score": 0.601,
      "rr_intervals": [
        659.9635427422359,
        667.1249578736594,
        664.578416651129,
        653.4165506719634
      ]
    },
    {
      "ts": "2026-04-07T19:58:44.654000",
      "bpm": 90.8,
      "temp_c": 28.7,
      "fsr_raw": 31,
      "stress_score": 0.441,
      "rr_intervals": [
        666.3776818594282,
        649.7009975756365,
        648.7581208772351,
        664.2579591108725
      ]
    },
    {
      "ts": "2026-04-07T19:58:47.900000",
      "bpm": 91.1,
      "temp_c": 28.81,
      "fsr_raw": 24,
      "stress_score": 0.414,
      "rr_intervals": [
        669.059281030402,
        643.9722212661005,
        646.7081574692601,
        686.1168377952636
      ]
    },
    {
      "ts": "2026-04-07T19:58:51.207000",
      "bpm": 33.1,
      "temp_c": 28.85,
      "fsr_raw": 10,
      "stress_score": 0.72,
      "rr_intervals": [
        1468.2922344786214,
        1465.2304216187874,
        1475.0290845340203,
        1494.4035424387598
      ]
    },
    {
      "ts": "2026-04-07T19:58:54.162000",
      "bpm": 90.1,
      "temp_c": 28.8,
      "fsr_raw": 13,
      "stress_score": 0.662,
      "rr_intervals": [
        687.8315263781351,
        614.1181572520944,
        640.8930519031398,
        667.0005813381343
      ]
    },
    {
      "ts": "2026-04-07T19:58:57.182000",
      "bpm": 90.7,
      "temp_c": 28.92,
      "fsr_raw": 32,
      "stress_score": 0.707,
      "rr_intervals": [
        632.5675159904964,
        645.6573800552036,
        661.3777654806975,
        656.5211342560241
      ]
    },
    {
      "ts": "2026-04-07T19:59:00.204000",
      "bpm": 90.5,
      "temp_c": 29.04,
      "fsr_raw": 28,
      "stress_score": 0.618,
      "rr_intervals": [
        668.3101872004389,
        670.1938539419077,
        644.6964790261696,
        648.0181772381559
      ]
    },
    {
      "ts": "2026-04-07T19:59:03.235000",
      "bpm": 87.1,
      "temp_c": 29.0,
      "fsr_raw": 1,
      "stress_score": 0.746,
      "rr_intervals": [
        699.0162120100445,
        645.5463852443194,
        711.0554448458718,
        678.7879030210622
      ]
    },
    {
      "ts": "2026-04-07T19:59:05.979000",
      "bpm": 87.4,
      "temp_c": 28.83,
      "fsr_raw": 12,
      "stress_score": 0.693,
      "rr_intervals": [
        695.0582606127537,
        686.4881128159982,
        672.7937730112185,
        692.2820041741581
      ]
    },
    {
      "ts": "2026-04-07T19:59:09.200000",
      "bpm": 88.6,
      "temp_c": 28.97,
      "fsr_raw": 25,
      "stress_score": 0.764,
      "rr_intervals": [
        642.5265553361605,
        673.4331051946355,
        687.1902714282837,
        660.3517810763058
      ]
    },
    {
      "ts": "2026-04-07T19:59:12.305000",
      "bpm": 21.6,
      "temp_c": 28.9,
      "fsr_raw": 17,
      "stress_score": 0.485,
      "rr_intervals": [
        1500.0,
        1462.9013565602893,
        1500.0,
        1500.0
      ]
    },
    {
      "ts": "2026-04-07T19:59:15.201000",
      "bpm": 89.4,
      "temp_c": 28.9,
      "fsr_raw": 2,
      "stress_score": 0.657,
      "rr_intervals": [
        680.913696446179,
        687.3739457243315,
        668.3929686860739,
        661.1588714764434
      ]
    }
  ]
}